xcdn/__init__.py
xcdn/ast.py
xcdn/error.py
xcdn/lexer.py
xcdn/parser.py
xcdn/ser.py
xcdn-0.1.0.dist-info/licenses/LICENSE
xcdn-0.1.0.dist-info/METADATA
xcdn-0.1.0.dist-info/WHEEL
xcdn-0.1.0.dist-info/top_level.txt
xcdn-0.1.0.dist-info/RECORD
