Metadata-Version: 2.4
Name: xcdn
Version: 0.1.0
Summary: A complete Python library to parse, serialize and deserialize xCDN — eXtensible Cognitive Data Notation
Author-email: Gioele Stefano Luca Fierro <your.email@example.com>
License: MIT
Project-URL: Homepage, https://github.com/gslf/xCDN
Project-URL: Repository, https://github.com/gslf/xCDN-Python
Project-URL: Documentation, https://github.com/gslf/xCDN-Python/blob/main/README.md
Project-URL: Bug Tracker, https://github.com/gslf/xCDN-Python/issues
Keywords: xcdn,parser,serializer,data-notation,configuration,json-alternative
Classifier: Development Status :: 4 - Beta
Classifier: Intended Audience :: Developers
Classifier: License :: OSI Approved :: MIT License
Classifier: Programming Language :: Python :: 3
Classifier: Programming Language :: Python :: 3.8
Classifier: Programming Language :: Python :: 3.9
Classifier: Programming Language :: Python :: 3.10
Classifier: Programming Language :: Python :: 3.11
Classifier: Programming Language :: Python :: 3.12
Classifier: Topic :: Software Development :: Libraries :: Python Modules
Classifier: Topic :: Text Processing :: Markup
Requires-Python: >=3.8
License-File: LICENSE
Provides-Extra: dev
Requires-Dist: pytest>=9.0.0; extra == "dev"
Requires-Dist: colorama>=0.4.6; extra == "dev"
Dynamic: license-file
